pytest_ipynb2/__init__.py
pytest_ipynb2/_cellpath.py
pytest_ipynb2/_parser.py
pytest_ipynb2/_pytester_helpers.py
pytest_ipynb2/plugin.py
tests/conftest.py
tests/test_collection.py
tests/test_collectiontree.py
tests/test_commandline.py
tests/test_execution.py
tests/test_fixtures.py
tests/test_parsenotebook.py
tests/assets/import_ipytest.py
tests/assets/notebook.py
tests/assets/test_class.py
tests/assets/test_failing.py
tests/assets/test_failing2.py
tests/assets/test_fixture.py
tests/assets/test_globals.py
tests/assets/test_module.py
tests/assets/test_othermodule.py
tests/assets/test_param.py
tests/assets/test_passing.py
pytest_ipynb2-0.5.0.dist-info/LICENSE
pytest_ipynb2-0.5.0.dist-info/METADATA
pytest_ipynb2-0.5.0.dist-info/WHEEL
pytest_ipynb2-0.5.0.dist-info/entry_points.txt
pytest_ipynb2-0.5.0.dist-info/top_level.txt
pytest_ipynb2-0.5.0.dist-info/RECORD
